ssr_utils/__init__.py
ssr_utils/errors.py
ssr_utils/ssr.py
ssr_utils-7.1.0.dist-info/LICENSE
ssr_utils-7.1.0.dist-info/METADATA
ssr_utils-7.1.0.dist-info/WHEEL
ssr_utils-7.1.0.dist-info/top_level.txt
ssr_utils-7.1.0.dist-info/RECORD
