Metadata-Version: 2.1
Name: ssr-utils
Version: 7.1.0
Summary: Shadowsocks(R) utils.
Home-page: https://github.com/neoctobers/py_ssr_utils
Author: @neoctobers
Author-email: neoctobers@gmail.com
License: UNKNOWN
Platform: UNKNOWN
Classifier: Programming Language :: Python :: 3
Classifier: License :: OSI Approved :: MIT License
Classifier: Operating System :: OS Independent
Requires-Dist: profig
Requires-Dist: requests-cache
Requires-Dist: cli-print
Requires-Dist: ip-query
Requires-Dist: qwert
Requires-Dist: proxy-fn
Requires-Dist: common-patterns
Requires-Dist: proxychains-conf-generator
